hatch_util/__about__.py
hatch_util/__init__.py
hatch_util/compose.py
hatch_util/convert.py
hatch_util/environ.py
hatch_util/hash_object.py
hatch_util/misc.py
hatch_util/parser_argument.py
hatch_util/period.py
hatch_util/string.py
hatch_util-0.0.2.dist-info/METADATA
hatch_util-0.0.2.dist-info/WHEEL
hatch_util-0.0.2.dist-info/licenses/LICENSE.txt
hatch_util-0.0.2.dist-info/RECORD
