Metadata-Version: 2.1
Name: hatch-util
Version: 0.0.2
Summary: i-util contain functions so useful for processing data projects
Project-URL: Documentation, https://github.com/unknown/hatch-util#readme
Project-URL: Issues, https://github.com/unknown/hatch-util/issues
Project-URL: Source, https://github.com/unknown/hatch-util
Author-email: HuynhSieu <sieu.huynh@innotech.vn>
License-Expression: MIT
License-File: LICENSE.txt
Keywords: iutil
Classifier: Development Status :: 4 - Beta
Classifier: Programming Language :: Python
Classifier: Programming Language :: Python :: 3.7
Classifier: Programming Language :: Python :: 3.8
Classifier: Programming Language :: Python :: 3.9
Classifier: Programming Language :: Python :: 3.10
Classifier: Programming Language :: Python :: 3.11
Classifier: Programming Language :: Python :: Implementation :: CPython
Classifier: Programming Language :: Python :: Implementation :: PyPy
Requires-Python: >=3.7
